aluminum-0.1.0.dist-info/METADATA
aluminum-0.1.0.dist-info/WHEEL
aluminum/abstract.py
aluminum/store.py
aluminum/bucket.py
aluminum/py.typed.py
aluminum/mapped_column.py
aluminum/operator.py
aluminum/__init__.py
aluminum/result.py
aluminum/engine.py
aluminum/select.py
aluminum/aluminum.pyi
aluminum/base.py
aluminum/aluminum.cpython-311-darwin.so
aluminum-0.1.0.dist-info/RECORD
